fatmanurprojects/__init__.py
fatmanurprojects-0.0.2.dist-info/METADATA
fatmanurprojects-0.0.2.dist-info/WHEEL
fatmanurprojects-0.0.2.dist-info/top_level.txt
fatmanurprojects-0.0.2.dist-info/RECORD
