Metadata-Version: 2.4
Name: fatmanurprojects
Version: 0.0.2
Summary: A basic statistics package
Author-email: fatmanuryvz <fatmanuryvz.3535@gmail.com>
License: MIT
Project-URL: Homepage, https://github.com/fatmanuryvz/fatmanurprojects
Requires-Python: >=3.7
